pydevicetree/__init__.py
pydevicetree/ast/__init__.py
pydevicetree/ast/directive.py
pydevicetree/ast/helpers.py
pydevicetree/ast/node.py
pydevicetree/ast/property.py
pydevicetree/ast/reference.py
pydevicetree/source/__init__.py
pydevicetree/source/grammar.py
pydevicetree/source/parser.py
tests/__init__.py
tests/test_devicetree.py
tests/test_exceptions.py
tests/test_full_trees.py
tests/test_grammar.py
tests/test_overlay.py
pydevicetree-0.0.13.dist-info/LICENSE
pydevicetree-0.0.13.dist-info/METADATA
pydevicetree-0.0.13.dist-info/WHEEL
pydevicetree-0.0.13.dist-info/top_level.txt
pydevicetree-0.0.13.dist-info/RECORD
