Metadata-Version: 2.1
Name: pydevicetree
Version: 0.0.13
Summary: A library for parsing Devicetree Source v1
Home-page: https://github.com/sifive/pydevicetree
Author: Nathaniel Graff
Author-email: nathaniel.graff@sifive.com
Classifier: Programming Language :: Python :: 3
Classifier: License :: OSI Approved :: Apache Software License
Classifier: Operating System :: OS Independent
Requires-Python: >=3.5
License-File: LICENSE
Requires-Dist: pyparsing
